DSSPparser/__init__.py
DSSPparser/cmdline.py
DSSPparser/parser.py
DSSPparser/pdbToxssp.py
DSSPparser-0.1.3.dist-info/LICENSE.txt
DSSPparser-0.1.3.dist-info/METADATA
DSSPparser-0.1.3.dist-info/WHEEL
DSSPparser-0.1.3.dist-info/entry_points.txt
DSSPparser-0.1.3.dist-info/top_level.txt
DSSPparser-0.1.3.dist-info/zip-safe
DSSPparser-0.1.3.dist-info/RECORD
