Metadata-Version: 2.1
Name: DSSPparser
Version: 0.1.3
Summary: parse protein secondary structure; dssp file; DSSP api interface; transform PDB format to dssp format
Home-page: https://github.com/wangleiofficial/DSSPparser
Author: wanglei
Author-email: wanglei94@hust.edu.cn
Maintainer: wanglei
License: MIT
Keywords: Bioinformation,DSSP
Classifier: Intended Audience :: Developers
Classifier: Intended Audience :: Science/Research
Classifier: License :: OSI Approved :: MIT License
Classifier: Operating System :: OS Independent
Classifier: Programming Language :: Python :: 2.7
Classifier: Programming Language :: Python :: 3.3
Classifier: Programming Language :: Python :: 3.4
Classifier: Programming Language :: Python :: 3.5
License-File: LICENSE.txt
Requires-Dist: pandas
Requires-Dist: requests
Requires-Dist: biopython
